bump/__init__.py
bump_cli-0.5.0.dist-info/licenses/LICENSE
bump_cli-0.5.0.dist-info/METADATA
bump_cli-0.5.0.dist-info/WHEEL
bump_cli-0.5.0.dist-info/entry_points.txt
bump_cli-0.5.0.dist-info/top_level.txt
bump_cli-0.5.0.dist-info/RECORD
