Metadata-Version: 2.4
Name: bump-cli
Version: 0.5.0
Summary: A command line tool for bumping git tag versions
Author-email: luiarthur <luiarthur@gmail.com>
Maintainer-email: luiarthur <luiarthur@gmail.com>
License: MIT License
Project-URL: Homepage, https://github.com/luiarthur/bump-cli
Project-URL: Repository, https://github.com/luiarthur/bump-cli
Project-URL: Issues, https://github.com/luiarthur/bump-cli/issues
Classifier: Operating System :: OS Independent
Classifier: Programming Language :: Python :: 3.8
Classifier: Programming Language :: Python :: 3.9
Classifier: Programming Language :: Python :: 3.10
Classifier: Programming Language :: Python :: 3.11
Classifier: Programming Language :: Python :: 3.12
Classifier: Programming Language :: Python :: 3.13
Classifier: Programming Language :: Python :: 3.14
Requires-Python: >=3.10
License-File: LICENSE
Requires-Dist: gitpython>=3.1.44
Requires-Dist: semver>=3.0.2
Requires-Dist: typer>=0.17.4
Dynamic: license-file
